github_actions_wizard/__init__.py
github_actions_wizard/aws.py
github_actions_wizard/cmd.py
github_actions_wizard/forms.py
github_actions_wizard/main.py
github_actions_wizard/pypi.py
github_actions_wizard/templates.py
github_actions_wizard/workflow.py
github_actions_wizard/jobs/__init__.py
github_actions_wizard/jobs/build_jobs.py
github_actions_wizard/jobs/deploy_jobs.py
github_actions_wizard/jobs/post_deploy_jobs.py
github_actions_wizard/jobs/test_jobs.py
github_actions_wizard-1.9.2.dist-info/licenses/LICENSE
github_actions_wizard-1.9.2.dist-info/METADATA
github_actions_wizard-1.9.2.dist-info/WHEEL
github_actions_wizard-1.9.2.dist-info/entry_points.txt
github_actions_wizard-1.9.2.dist-info/top_level.txt
github_actions_wizard-1.9.2.dist-info/RECORD
