Metadata-Version: 2.4
Name: github-actions-wizard
Version: 1.9.2
Summary: A simple wizard for generating GitHub Actions workflows for common tasks.
Author: cmdr2
License: MIT License
Project-URL: Homepage, https://github.com/cmdr2/github-actions-wizard
Project-URL: Repository, https://github.com/cmdr2/github-actions-wizard
Requires-Python: >=3.8
License-File: LICENSE
Requires-Dist: ruamel.yaml
Dynamic: license-file
